Workbook

Sheet 00_HUONG_DAN
A1: DTH BUSINESS CORE - BỘ DỮ LIỆU KIỂM THỬ UI XUYÊN SUỐT
A3: Mục tiêu | B3: Dùng một bộ dữ liệu nhất quán từ Landing Page → Submission → Lead → Phân phối → Qualification → Opportunity → Quotation → Payment → Customer.
A5: THÔNG SỐ ĐỢT KIỂM THỬ - CHỈ SỬA CÁC Ô MÀU XANH
A6: 1 | B6: Mã đợt test | C6: UITEST-HOSTING-01 | D6: Đổi mã này mỗi lần muốn tạo lại dữ liệu mà không xóa batch cũ.
A7: 2 | B7: Email nhận thư thực tế | C7: your.email@gmail.com | D7: Thay bằng email bạn kiểm soát. Workbook tự tạo plus-alias cho từng nhân vật. Nếu nhà cung cấp không hỗ trợ dấu +, nhập email riêng trực tiếp ở sheet 02.
A8: 3 | B8: Ngày bắt đầu đợt test | C8: =TODAY() | D8: Các ngày triển khai, đóng cơ hội, báo giá và thanh toán được tính tương đối từ ngày này.
A9: 4 | B9: Mã số thuế Company test | C9: 9999999999 | D9: Chỉ dùng cho dữ liệu test. Lệnh reset mặc định nhận diện MST này.
A10: 5 | B10: Tên Company test | C10: Công ty TNHH Giải pháp Số Minh Phát - TEST | D10: Giữ nguyên để kiểm tra chống trùng Company.
A11: 6 | B11: Landing Page | C11: Giới thiệu dịch vụ Hosting | D11: Landing Page đã có sẵn.
A12: 7 | B12: Ads Campaign | C12: Chiến dịch Hosting Siêu Tốc Q3/2026 | D12: Chiến dịch đã có sẵn.
A14: QUY TẮC SỬ DỤNG
A15: 1 | B15: Luôn chạy sheet 07_RESET ở chế độ dry-run trước khi xóa thật.
A16: 2 | B16: Bộ A là Golden Path chính; tiếp tục dùng cùng Lead này cho Qualification, Opportunity, Quotation, Payment và Customer.
A17: 3 | B17: Bộ C dùng kiểm tra hai người cùng Company và nguyên tắc Account Owner.
A18: 4 | B18: Bộ F dùng kiểm tra cùng Contact gửi nhu cầu mới; Contact không được nhân đôi và Lead cũ không bị ghi đè.
A19: 5 | B19: Submission là bản gốc; không sửa câu trả lời cũ sau khi khách gửi.
A20: 6 | B20: Đổi Mã đợt test ở ô C6 để sinh email alias mới khi cần chạy lại mà không reset.

Sheet 01_CAU_HINH_FORM
A1: CẤU HÌNH FORM TEMPLATE CHUẨN CHO LANDING PAGE HOSTING
A3: STT | B3: Áp dụng | C3: Nhãn trường | D3: Khóa field | E3: Loại | F3: Bắt buộc | G3: Nơi lưu dữ liệu | H3: Validation | I3: Options / Ghi chú
A4: 1 | B4: Cá nhân | C4: Họ | D4: first_name | E4: Văn bản | F4: Có | G4: Contact cá nhân → Họ | H4: required|max:100
A5: 2 | B5: Cá nhân | C5: Tên | D5: last_name | E5: Văn bản | F5: Có | G5: Contact cá nhân → Tên | H5: required|max:100
A6: 3 | B6: Cá nhân | C6: Giới tính | D6: gender | E6: Chọn | F6: Không | G6: Contact cá nhân → Giới tính | I6: male=Nam; female=Nữ; other=Khác
A7: 4 | B7: Cá nhân | C7: Email cá nhân | D7: email | E7: Email | F7: Có | G7: Contact cá nhân → Email | H7: required|email|max:255
A8: 5 | B8: Cá nhân | C8: Số điện thoại | D8: phone | E8: Điện thoại | F8: Có | G8: Contact cá nhân → Số điện thoại | H8: required|max:30
A9: 6 | B9: Cá nhân | C9: Dịch vụ quan tâm | D9: service_interest | E9: Chọn | F9: Có | G9: Lead → Dịch vụ quan tâm | H9: required | I9: hosting_basic=Web Hosting - Bình thường; hosting_pro=Web Hosting - Trung bình; hosting_vip=Web Hosting - Cao cấp
A10: 7 | B10: Doanh nghiệp | C10: Chức vụ | D10: contact_position | E10: Chọn | F10: Có | G10: Contact doanh nghiệp → Chức vụ | H10: required|max:150 | I10: it_manager=Trưởng phòng CNTT; director=Giám đốc; chief_accountant=Kế toán trưởng
A11: 8 | B11: Doanh nghiệp | C11: Tên doanh nghiệp | D11: company_name | E11: Văn bản | F11: Có | G11: Company → Tên pháp lý | H11: required|max:255
A12: 9 | B12: Doanh nghiệp | C12: Mã số thuế | D12: tax_code | E12: Văn bản | F12: Có | G12: Company → Mã số thuế | H12: required|max:30
A13: 10 | B13: Doanh nghiệp | C13: Người đại diện liên hệ | D13: legal_representative | E13: Văn bản | F13: Có | G13: Contact doanh nghiệp → Người liên hệ | H13: required|max:255
A14: 11 | B14: Doanh nghiệp | C14: Số điện thoại công ty | D14: business_phone | E14: Điện thoại | F14: Có | G14: Contact doanh nghiệp → Điện thoại | H14: required|max:30
A15: 12 | B15: Doanh nghiệp | C15: Email doanh nghiệp | D15: business_email | E15: Email | F15: Có | G15: Contact doanh nghiệp → Email | H15: required|email|max:255
A16: 13 | B16: Doanh nghiệp | C16: Dịch vụ quan tâm | D16: service_interest | E16: Chọn | F16: Có | G16: Lead → Dịch vụ quan tâm | H16: required | I16: hosting_basic=Web Hosting - Bình thường; hosting_pro=Web Hosting - Trung bình; hosting_vip=Web Hosting - Cao cấp
A17: 14 | B17: Cả hai | C17: Số lượng website | D17: website_count | E17: Số | F17: Có | G17: Chỉ Submission + Lead snapshot | H17: integer|min:1|max:1000
A18: 15 | B18: Cả hai | C18: Nhà cung cấp hiện tại | D18: current_provider | E18: Văn bản | F18: Không | G18: Chỉ Submission + Lead snapshot | H18: max:150
A19: 16 | B19: Cả hai | C19: Cần chuyển dữ liệu | D19: migration_required | E19: Chọn | F19: Có | G19: Chỉ Submission + Lead snapshot | H19: required | I19: yes=Có; no=Không; unsure=Chưa xác định
A20: 17 | B20: Cả hai | C20: Ngày dự kiến triển khai | D20: expected_start_date | E20: Ngày | F20: Có | G20: Chỉ Submission + Lead snapshot | H20: required|after_or_equal:today
A21: 18 | B21: Cả hai | C21: Ngân sách dự kiến | D21: expected_budget | E21: Số | F21: Không | G21: Chỉ Submission + Lead snapshot | H21: numeric|min:0|max:1000000000
A22: 19 | B22: Cả hai | C22: Mô tả nhu cầu | D22: requirement_note | E22: Vùng văn bản | F22: Không | G22: Chỉ Submission + Lead snapshot | H22: max:1000

Sheet 02_DU_LIEU_FORM
A1: DỮ LIỆU NHẬP FORM - DÙNG LẠI CHO TOÀN BỘ QUÁ TRÌNH TEST
A3: Bộ | B3: Mục đích | C3: Loại form | D3: Họ / Chức vụ | E3: Tên / Người liên hệ | F3: Email | G3: Điện thoại | H3: Tên doanh nghiệp | I3: Mã số thuế | J3: Dịch vụ | K3: Số website | L3: Nhà cung cấp | M3: Chuyển dữ liệu | N3: Ngày triển khai | O3: Ngân sách | P3: Mô tả nhu cầu | Q3: Kết quả chính | R3: Trạng thái test
A4: A | B4: Golden Path B2B | C4: Doanh nghiệp | D4: Trưởng phòng CNTT | E4: Nguyễn Minh Khoa | F4: =LEFT('00_HUONG_DAN'!$C$7,FIND("@",'00_HUONG_DAN'!$C$7)-1)&"+dth."&LOWER(SUBSTITUTE('00_HUONG_DAN'!$C$6,"-","."))&".b2b001"&MID('00_HUONG_DAN'!$C$7,FIND("@",'00_HUONG_DAN'!$C$7),LEN('00_HUONG_DAN'!$C$7)) | G4: 0900001001 | H4: ='00_HUONG_DAN'!$C$10 | I4: ='00_HUONG_DAN'!$C$9 | J4: hosting_pro | K4: 5 | L4: AZDIGI | M4: yes | N4: ='00_HUONG_DAN'!$C$8+7 | O4: 5000000 | P4: Chuyển 5 website WordPress, hạn chế gián đoạn, hỗ trợ SSL và backup. | Q4: Tạo 1 Submission, 1 Contact, 1 Company, 1 Lead đủ dữ liệu. Dùng Lead này cho toàn bộ Golden Path. | R4: Chưa test
A5: B | B5: Lead cá nhân | C5: Cá nhân | D5: Lê | E5: Thu Hà | F5: =LEFT('00_HUONG_DAN'!$C$7,FIND("@",'00_HUONG_DAN'!$C$7)-1)&"+dth."&LOWER(SUBSTITUTE('00_HUONG_DAN'!$C$6,"-","."))&".personal001"&MID('00_HUONG_DAN'!$C$7,FIND("@",'00_HUONG_DAN'!$C$7),LEN('00_HUONG_DAN'!$C$7)) | G5: 0900001002 | J5: hosting_basic | K5: 1 | L5: Chưa có | M5: no | N5: ='00_HUONG_DAN'!$C$8+10 | O5: 1000000 | P5: Website giới thiệu cá nhân, cần SSL và hướng dẫn quản trị. | Q5: Tạo Contact cá nhân + Lead; không tạo Company. | R5: Chưa test
A6: C | B6: Người liên hệ thứ hai cùng Company | C6: Doanh nghiệp | D6: Kế toán trưởng | E6: Trần Ngọc Mai | F6: =LEFT('00_HUONG_DAN'!$C$7,FIND("@",'00_HUONG_DAN'!$C$7)-1)&"+dth."&LOWER(SUBSTITUTE('00_HUONG_DAN'!$C$6,"-","."))&".b2b002"&MID('00_HUONG_DAN'!$C$7,FIND("@",'00_HUONG_DAN'!$C$7),LEN('00_HUONG_DAN'!$C$7)) | G6: 0900001003 | H6: ='00_HUONG_DAN'!$C$10 | I6: ='00_HUONG_DAN'!$C$9 | J6: hosting_vip | K6: 12 | L6: Vietnix | M6: unsure | N6: ='00_HUONG_DAN'!$C$8+14 | O6: 15000000 | P6: Đánh giá tài nguyên và chuyển 12 website theo từng đợt. | Q6: Không tạo Company thứ hai; Company có 2 Contact; Lead mới giữ nhu cầu riêng. | R6: Chưa test
A7: D | B7: Chống nhấn gửi hai lần | C7: Doanh nghiệp | D7: Trưởng phòng CNTT | E7: Nguyễn Minh Khoa | F7: =LEFT('00_HUONG_DAN'!$C$7,FIND("@",'00_HUONG_DAN'!$C$7)-1)&"+dth."&LOWER(SUBSTITUTE('00_HUONG_DAN'!$C$6,"-","."))&".duplicate001"&MID('00_HUONG_DAN'!$C$7,FIND("@",'00_HUONG_DAN'!$C$7),LEN('00_HUONG_DAN'!$C$7)) | G7: 0900001004 | H7: ='00_HUONG_DAN'!$C$10 | I7: ='00_HUONG_DAN'!$C$9 | J7: hosting_pro | K7: 5 | L7: AZDIGI | M7: yes | N7: ='00_HUONG_DAN'!$C$8+7 | O7: 5000000 | P7: Nhấn nút gửi liên tiếp hai lần. | Q7: Chỉ 1 Submission và 1 Lead. | R7: Chưa test
A8: E | B8: Validation giá trị giả | C8: DevTools/API | E8: Invalid Service | F8: =LEFT('00_HUONG_DAN'!$C$7,FIND("@",'00_HUONG_DAN'!$C$7)-1)&"+dth."&LOWER(SUBSTITUTE('00_HUONG_DAN'!$C$6,"-","."))&".invalid001"&MID('00_HUONG_DAN'!$C$7,FIND("@",'00_HUONG_DAN'!$C$7),LEN('00_HUONG_DAN'!$C$7)) | G8: 0900001005 | J8: hosting_free_forever | K8: 1 | L8: Không có | M8: no | N8: ='00_HUONG_DAN'!$C$8+7 | O8: 0 | P8: Gửi giá trị dịch vụ không thuộc options. | Q8: Backend từ chối; không tạo Contact/Submission/Lead dở dang. | R8: Chưa test
A9: F | B9: Cùng Contact, nhu cầu mới | C9: Cá nhân | D9: Lê | E9: Thu Hà | F9: =LEFT('00_HUONG_DAN'!$C$7,FIND("@",'00_HUONG_DAN'!$C$7)-1)&"+dth."&LOWER(SUBSTITUTE('00_HUONG_DAN'!$C$6,"-","."))&".personal001"&MID('00_HUONG_DAN'!$C$7,FIND("@",'00_HUONG_DAN'!$C$7),LEN('00_HUONG_DAN'!$C$7)) | G9: 0900001002 | J9: hosting_vip | K9: 3 | L9: Nhà cung cấp khác | M9: yes | N9: ='00_HUONG_DAN'!$C$8+21 | O9: 8000000 | P9: Nâng cấp lên VIP cho 3 website và cần chuyển dữ liệu. | Q9: Vẫn 1 Contact cá nhân; tạo Submission và Lead mới; Lead B không đổi. | R9: Chưa test

Sheet 03_PHAN_PHOI
A1: KIỂM THỬ TỰ ĐỘNG PHÂN PHỐI LEAD
A3: Bước | B3: Dữ liệu sử dụng | C3: Thao tác UI | D3: Điều kiện trước | E3: Kết quả trên Lead | F3: Kết quả trên Company/Submission | G3: Rủi ro cần chặn | H3: Trạng thái
A4: 1 | B4: Bộ A | C4: Nhấn Tự động phân phối | D4: Lead A đủ dữ liệu, Company đã xác định | E4: Có nhân viên phụ trách; assigned_at được ghi; trạng thái phù hợp | F4: Submission chuyển Đã phân phối; Company có Account Owner | G4: Không giao cho nhân viên ngừng hoạt động/không nhận khách | H4: Chưa test
A5: 2 | B5: Bộ C | C5: Chạy tự động phân phối sau A | D5: Cùng MST và cùng Company với A | E5: Lead C ưu tiên cùng nhân viên với Lead A | F5: Account Owner Company không bị đổi ngẫu nhiên | G5: Hai nhân viên cùng gọi một doanh nghiệp | H5: Chưa test
A6: 3 | B6: Bộ B | C6: Chạy tự động phân phối | D6: Lead cá nhân đủ dữ liệu | E6: Được phân cho nhân viên hợp lệ | F6: Không tạo Company | G6: Lead cá nhân bị chặn vì không có Company | H6: Chưa test
A7: 4 | B7: Lead thiếu dữ liệu/backfill | C7: Chạy tự động phân phối | D7: intake_ready=false | E7: Không được phân phối | F7: Giữ trạng thái Cần kiểm tra | G7: Giao Lead thiếu dịch vụ cho Sales | H7: Chưa test

Sheet 04_QUALIFICATION
A1: DỮ LIỆU QUALIFICATION - DÙNG LEAD A LÀM GOLDEN PATH
A3: Bước | B3: Lead | C3: Trạng thái | D3: Ưu tiên | E3: Điểm | F3: Giá trị ước tính | G3: Ngày follow-up | H3: Ghi chú / Kết quả liên hệ | I3: Kết quả mong muốn | J3: Trạng thái test
A4: 1 | B4: Bộ A | C4: Đang liên hệ | D4: Cao | E4: 70 | F4: 3850000 | G4: ='00_HUONG_DAN'!$C$8+1 | H4: Đã gọi lần đầu; khách xác nhận có 5 website WordPress và cần chuyển dữ liệu. | I4: Ghi activity/note; first_contacted_at có giá trị; chưa tạo Opportunity. | J4: Chưa test
A5: 2 | B5: Bộ A | C5: Theo dõi | D5: Cao | E5: 80 | F5: 3850000 | G5: ='00_HUONG_DAN'!$C$8+3 | H5: Khách gửi thông tin dung lượng và lịch truy cập thấp điểm. | I5: next_follow_up_at cập nhật; lịch sử bước 1 vẫn còn. | J5: Chưa test
A6: 3 | B6: Bộ A | C6: Đủ điều kiện | D6: Cao | E6: 88 | F6: 3850000 | G6: ='00_HUONG_DAN'!$C$8+5 | H6: Xác nhận ngân sách 5 triệu, triển khai trong 1 tuần, người quyết định là Giám đốc. | I6: Cho phép chuyển thành Opportunity; qualified_at và người xác minh được ghi. | J6: Chưa test
A7: 4 | B7: Bộ B | C7: Không đủ điều kiện | D7: Thường | E7: 25 | F7: 1000000 | H7: Khách chỉ tham khảo, chưa có kế hoạch triển khai trong 6 tháng. | I7: Không tạo Opportunity; lý do không đủ điều kiện bắt buộc. | J7: Chưa test

Sheet 05_OPPORTUNITY_QUOTE
A1: GOLDEN PATH SALES - OPPORTUNITY, QUOTATION, PAYMENT, CUSTOMER
A3: A. OPPORTUNITY
A4: Bước | B4: Trường/Thao tác | C4: Giá trị nhập | D4: Stage kỳ vọng | E4: Xác suất | F4: Giá trị | G4: Ngày dự kiến chốt | H4: Đối tượng liên kết | I4: Kết quả mong muốn | J4: Trạng thái
A5: 1 | B5: Chuyển Lead A thành Opportunity | C5: Hosting Pro 12 tháng + chuyển 5 website - Minh Phát | D5: qualified | E5: 50 | F5: 3850000 | G5: ='00_HUONG_DAN'!$C$8+14 | H5: Lead A + Company Minh Phát + Nguyễn Minh Khoa | I5: Chỉ tạo 1 Opportunity từ Lead A; owner kế thừa đúng. | J5: Chưa test
A6: 2 | B6: Chuyển stage | C6: Đã xác nhận nhu cầu và giải pháp kỹ thuật | D6: proposal | E6: 65 | F6: 3850000 | G6: ='00_HUONG_DAN'!$C$8+14 | H6: Opportunity của A | I6: Ghi lịch sử stage/interactions. | J6: Chưa test
A7: 3 | B7: Sau khi gửi báo giá | C7: Khách đang xem xét điều khoản | D7: negotiation | E7: 80 | F7: 3850000 | G7: ='00_HUONG_DAN'!$C$8+14 | H7: Opportunity của A | I7: Không được đánh dấu Won khi chưa thanh toán. | J7: Chưa test
A10: B. BÁO GIÁ - CÁC DÒNG HÀNG VÀ SỐ TIỀN KIỂM SOÁT
A11: STT | B11: Hạng mục | C11: Mã tham chiếu | D11: Số lượng | E11: Đơn giá | F11: Thành tiền | G11: Giảm giá | H11: VAT | I11: Ghi chú | J11: Trạng thái
A12: 1 | B12: Hosting Pro 12 tháng | C12: hosting_pro_annual | D12: 1 | E12: 1188000 | F12: =D12*E12 | G12: 0 | H12: 0 | I12: 99.000đ/tháng x 12 tháng | J12: Chưa test
A13: 2 | B13: Chuyển dữ liệu WordPress | C13: wp_migration | D13: 5 | E13: 500000 | F13: =D13*E13 | G13: 188000 | H13: 0 | I13: Chuyển 5 website | J13: Chưa test
A14: 3 | B14: SSL | C14: ssl_free | D14: 1 | E14: 0 | F14: =D14*E14 | G14: 0 | H14: 0 | I14: Miễn phí | J14: Chưa test
E15: Tạm tính | F15: =SUM(F12:F14)
E16: Tổng giảm giá | F16: =SUM(G12:G14)
E17: Giá trị tính thuế | F17: =F15-F16
E18: VAT 10% | F18: =F17*10%
E19: Tổng thanh toán | F19: =F17+F18
A22: C. THANH TOÁN VÀ CHUYỂN CUSTOMER
A23: Bước | B23: Thao tác | C23: Giá trị | D23: Ngày | E23: Opportunity | F23: Quotation | G23: Customer | H23: Đối soát bắt buộc | I23: Kết quả mong muốn | J23: Trạng thái
A24: 1 | B24: Gửi báo giá | C24: Người nhận là email Bộ A | D24: ='00_HUONG_DAN'!$C$8+5 | E24: Giữ negotiation | F24: Sent | G24: Chưa có | H24: Có email log và PDF; snapshot không đổi khi Contact sửa | I24: Khách nhận đúng báo giá và public link hoạt động | J24: Chưa test
A25: 2 | B25: Khách chấp nhận báo giá | C25: Accepted | D25: ='00_HUONG_DAN'!$C$8+7 | E25: Giữ negotiation | F25: Accepted | G25: Chưa có | H25: Không tự tạo Customer trước thanh toán | I25: accepted_at được ghi | J25: Chưa test
A26: 3 | B26: Xác nhận thanh toán | C26: ='00_HUONG_DAN'!$C$6&"-PAY-001" | D26: ='00_HUONG_DAN'!$C$8+8 | E26: Won | F26: Paid | G26: Được tạo/chuyển đổi | H26: Tổng doanh thu = Tổng thanh toán; người xác minh được ghi | I26: Opportunity Won chỉ sau khi payment=Paid; tạo đúng Customer | J26: Chưa test

Sheet 06_DOI_SOAT
A1: ĐỐI SOÁT DỮ LIỆU LIÊN MODULE
A3: STT | B3: Mốc kiểm tra | C3: Thực thể | D3: Số lượng kỳ vọng | E3: Khóa đối chiếu | F3: Dữ liệu phải khớp | G3: Lỗi nghiêm trọng | H3: Trạng thái
A4: 1 | B4: Sau khi gửi A | C4: Submission / Contact / Company / Lead / Qualification | D4: 1 / 1 / 1 / 1 / 1 | E4: Email A, MST 9999999999 | F4: Dịch vụ hosting_pro; 5 website; ngân sách 5.000.000 | G4: Lead thiếu dịch vụ, Company trùng MST, form_answers không hiển thị
A5: 2 | B5: Sau khi gửi B | C5: Submission / Contact / Company / Lead | D5: 1 / 1 / 0 / 1 | E5: Email B, SĐT 0900001002 | F5: Lead cá nhân đủ dữ liệu | G5: Tạo Company cho cá nhân
A6: 3 | B6: Sau khi gửi C | C6: Company / Contact / Lead | D6: 1 Company / 2 Contact / 2 Lead B2B | E6: Cùng MST | F6: Hai Lead có snapshot khác nhau | G6: Tạo Company thứ hai hoặc ghi đè nhu cầu A
A7: 4 | B7: Sau phân phối A+C | C7: Lead / Company Account Owner | D7: 2 Lead cùng owner | E7: company_id | F7: assigned_staff_id của A và C nhất quán | G7: Hai nhân viên phụ trách cùng Company
A8: 5 | B8: Sau Qualification A | C8: Lead / Qualification / Activity | D8: 1 Lead / 1 Qualification / nhiều Activity | E8: lead_id | F8: Trạng thái, score, follow-up, ghi chú đúng lịch sử | G8: Sửa trạng thái làm mất note cũ
A9: 6 | B9: Sau tạo Opportunity | C9: Lead / Opportunity | D9: 1 Lead → 1 Opportunity | E9: lead_id unique | F9: Company, Contact, Owner, dịch vụ kế thừa | G9: Một Lead tạo hai Opportunity
A10: 7 | B10: Sau báo giá | C10: Opportunity / Quotation / Items | D10: 1 Opportunity / 1 Quotation / 3 Items | E10: opportunity_id | F10: Tổng thanh toán 3.850.000 VND | G10: Sai tiền, sai VAT, snapshot sai khách
A11: 8 | B11: Sau thanh toán | C11: Quotation / Opportunity / Customer | D11: Paid / Won / 1 Customer | E11: opportunity_id + contact/company | F11: Doanh thu 3.850.000; converted_from_opportunity đúng | G11: Customer tạo trước Paid hoặc tạo trùng

Sheet 07_RESET
A1: XÓA DỮ LIỆU TEST CŨ AN TOÀN
A3: Bước | B3: Mục đích | C3: Lệnh Git Bash
A4: 1 | B4: Đặt file command vào đúng source | C4: Giải nén DTH-ui-test-reset-overlay.zip tại thư mục marketing-email-laravel-v12
A5: 2 | B5: Xóa cache để Artisan nhận command | C5: php artisan optimize:clear
A6: 3 | B6: Xem trước phạm vi ba Lead cũ | C6: php artisan crm:reset-ui-test-data --dry-run
A7: 4 | B7: Xóa thật và reset sequence nếu toàn bộ bảng nghiệp vụ đã trống | C7: php artisan crm:reset-ui-test-data --force --reset-sequences
A8: 5 | B8: Kiểm tra sau xóa | C8: php artisan crm:reset-ui-test-data --dry-run
A9: 6 | B9: Xóa theo Mã đợt test trong workbook | C9: php artisan crm:reset-ui-test-data --batch=UITEST-HOSTING-01 --dry-run
A10: 7 | B10: Xóa một nhóm email tùy chỉnh | C10: php artisan crm:reset-ui-test-data --dry-run --email="email1" --email="email2" --tax-code="9999999999"
A12: DỮ LIỆU MẶC ĐỊNH COMMAND NHẬN DIỆN
B13: Email 1 | C13: lead.hosting.b2b.001@example.com
B14: Email 2 | C14: lead.hosting.personal.001@example.com
B15: Email 3 | C15: lead.hosting.b2b.002@example.com
B16: MST | C16: 9999999999
A18: CẢNH BÁO
B19: Không chạy trên production. Command tự chặn APP_ENV=production, nhưng vẫn phải kiểm tra đúng database trước khi dùng.
